text_histogram3.py
text_histogram3-1.0.0.dist-info/LICENSE
text_histogram3-1.0.0.dist-info/METADATA
text_histogram3-1.0.0.dist-info/WHEEL
text_histogram3-1.0.0.dist-info/top_level.txt
text_histogram3-1.0.0.dist-info/zip-safe
text_histogram3-1.0.0.dist-info/RECORD
