Metadata-Version: 2.1
Name: text-histogram3
Version: 1.0.0
Summary: A dependency-free library to quickly make ascii histograms from data.
Home-page: https://github.com/basnijholt/text_histogram3
Author: Bas Nijholt, Andy Kish, Jehiah Czebotar
Author-email: bas@nijho.lt
License: Apache License, Version 2.0
Platform: UNKNOWN
Classifier: Programming Language :: Python :: 3
Classifier: Environment :: Console
Classifier: Intended Audience :: Developers
Classifier: Topic :: Terminals
